{
  "_type": "export",
  "__export_format": 4,
  "__export_date": "2024-10-27T01:24:50.079Z",
  "__export_source": "insomnia.desktop.app:v10.0.0",
  "resources": [
    {
      "_id": "req_16ad96f78e9a46f599d904935ee5fe02",
      "parentId": "fld_c2b3046c63c944ed9cc6ebb369e7d083",
      "modified": 1729991206772,
      "created": 1729989017560,
      "url": "{{ _['server-manager-service-url'] }}/servers",
      "name": "servers",
      "description": "",
      "method": "POST",
      "body": {
        "mimeType": "application/json",
        "text": "{\n\t\"applicationName\": \"abioticfactor\",\n\t\"containerName\": \"houseofabiotichomies\"\n}"
      },
      "parameters": [],
      "headers": [
        { "name": "Content-Type", "value": "application/json" },
        { "name": "User-Agent", "value": "insomnia/10.0.0" }
      ],
      "authentication": {},
      "metaSortKey": -1729988719081,
      "isPrivate": false,
      "pathParameters": [],
      "settingStoreCookies": true,
      "settingSendCookies": true,
      "settingDisableRenderRequestBody": false,
      "settingEncodeUrl": true,
      "settingRebuildPath": true,
      "settingFollowRedirects": "global",
      "_type": "request"
    },
    {
      "_id": "fld_c2b3046c63c944ed9cc6ebb369e7d083",
      "parentId": "wrk_scratchpad",
      "modified": 1729992278573,
      "created": 1729988712348,
      "name": "server-manager-service",
      "description": "",
      "environment": {
        "server-manager-service-url": "localhost:3000",
        "server-manager-service-server-id": ""
      },
      "environmentPropertyOrder": {
        "&": ["server-manager-service-url", "server-manager-service-server-id"]
      },
      "metaSortKey": -1729988712348,
      "_type": "request_group"
    },
    {
      "_id": "wrk_scratchpad",
      "parentId": null,
      "modified": 1716635192520,
      "created": 1716635192520,
      "name": "Scratch Pad",
      "description": "",
      "scope": "collection",
      "_type": "workspace"
    },
    {
      "_id": "req_82bdcd8b7cfb45f2b48f5514c31ca48b",
      "parentId": "fld_c2b3046c63c944ed9cc6ebb369e7d083",
      "modified": 1729990447443,
      "created": 1729988717277,
      "url": "{{ _['server-manager-service-url'] }}/servers",
      "name": "servers",
      "description": "",
      "method": "GET",
      "body": {},
      "parameters": [],
      "headers": [{ "name": "User-Agent", "value": "insomnia/10.0.0" }],
      "authentication": {},
      "metaSortKey": -1729988718981,
      "isPrivate": false,
      "pathParameters": [],
      "afterResponseScript": "",
      "settingStoreCookies": true,
      "settingSendCookies": true,
      "settingDisableRenderRequestBody": false,
      "settingEncodeUrl": true,
      "settingRebuildPath": true,
      "settingFollowRedirects": "global",
      "_type": "request"
    },
    {
      "_id": "req_e0ce96970d8348eb9f065bef60a3817a",
      "parentId": "fld_c2b3046c63c944ed9cc6ebb369e7d083",
      "modified": 1729990578237,
      "created": 1729989639164,
      "url": "{{ _['server-manager-service-url'] }}/servers/:id",
      "name": "servers by id",
      "description": "",
      "method": "GET",
      "body": {},
      "parameters": [],
      "headers": [{ "name": "User-Agent", "value": "insomnia/10.0.0" }],
      "authentication": {},
      "metaSortKey": -1729988713577.5,
      "isPrivate": false,
      "pathParameters": [
        { "name": "id", "value": "{{ _['server-manager-service-server-id'] }}" }
      ],
      "afterResponseScript": "",
      "settingStoreCookies": true,
      "settingSendCookies": true,
      "settingDisableRenderRequestBody": false,
      "settingEncodeUrl": true,
      "settingRebuildPath": true,
      "settingFollowRedirects": "global",
      "_type": "request"
    },
    {
      "_id": "req_17d2d795104e417bb141126d8805a5a1",
      "parentId": "fld_c2b3046c63c944ed9cc6ebb369e7d083",
      "modified": 1729990353523,
      "created": 1729989307420,
      "url": "{{ _['server-manager-service-url'] }}/servers/:id",
      "name": "servers",
      "description": "",
      "method": "PATCH",
      "body": {
        "mimeType": "application/json",
        "text": "{\n\t\"applicationName\": \"valheim\",\n\t\"containerName\": \"oldzanesworld\"\n}"
      },
      "parameters": [],
      "headers": [
        { "name": "Content-Type", "value": "application/json" },
        { "name": "User-Agent", "value": "insomnia/10.0.0" }
      ],
      "authentication": {},
      "metaSortKey": -1729988702770.5,
      "isPrivate": false,
      "pathParameters": [
        { "name": "id", "value": "{{ _['server-manager-service-server-id'] }}" }
      ],
      "settingStoreCookies": true,
      "settingSendCookies": true,
      "settingDisableRenderRequestBody": false,
      "settingEncodeUrl": true,
      "settingRebuildPath": true,
      "settingFollowRedirects": "global",
      "_type": "request"
    },
    {
      "_id": "req_17834c8374af47e4872594f1d9949557",
      "parentId": "fld_c2b3046c63c944ed9cc6ebb369e7d083",
      "modified": 1729990417215,
      "created": 1729990412307,
      "url": "{{ _['server-manager-service-url'] }}/servers/:id",
      "name": "servers by id",
      "description": "",
      "method": "DELETE",
      "body": {},
      "parameters": [],
      "headers": [{ "name": "User-Agent", "value": "insomnia/10.0.0" }],
      "authentication": {},
      "metaSortKey": -1729988702670.5,
      "isPrivate": false,
      "pathParameters": [
        { "name": "id", "value": "{{ _['server-manager-service-server-id'] }}" }
      ],
      "settingStoreCookies": true,
      "settingSendCookies": true,
      "settingDisableRenderRequestBody": false,
      "settingEncodeUrl": true,
      "settingRebuildPath": true,
      "settingFollowRedirects": "global",
      "_type": "request"
    },
    {
      "_id": "env_99d30891da4bdcebc63947a8fc17f076de878684",
      "parentId": "wrk_scratchpad",
      "modified": 1729991851361,
      "created": 1716635231848,
      "name": "Base Environment",
      "data": {},
      "dataPropertyOrder": {},
      "color": null,
      "isPrivate": false,
      "metaSortKey": 1716635231848,
      "_type": "environment"
    },
    {
      "_id": "jar_99d30891da4bdcebc63947a8fc17f076de878684",
      "parentId": "wrk_scratchpad",
      "modified": 1729990506795,
      "created": 1716635231851,
      "name": "Default Jar",
      "cookies": [],
      "_type": "cookie_jar"
    }
  ]
}
